setup.py
three/__init__.py
three/three.py
three.egg-info/PKG-INFO
three.egg-info/SOURCES.txt
three.egg-info/dependency_links.txt
three.egg-info/requires.txt
three.egg-info/top_level.txt